pause_transformer/__init__.py
pause_transformer/pause_transformer.py
pause_transformer-0.0.7.dist-info/LICENSE
pause_transformer-0.0.7.dist-info/METADATA
pause_transformer-0.0.7.dist-info/WHEEL
pause_transformer-0.0.7.dist-info/top_level.txt
pause_transformer-0.0.7.dist-info/RECORD
