Metadata-Version: 2.1
Name: pause-transformer
Version: 0.0.7
Summary: Pause Transformer
Home-page: https://github.com/lucidrains/pause-transformer
Author: Phil Wang
Author-email: lucidrains@gmail.com
License: MIT
Keywords: artificial intelligence,deep learning,adaptive computation
Classifier: Development Status :: 4 - Beta
Classifier: Intended Audience :: Developers
Classifier: Topic :: Scientific/Engineering :: Artificial Intelligence
Classifier: License :: OSI Approved :: MIT License
Classifier: Programming Language :: Python :: 3.6
License-File: LICENSE
Requires-Dist: einops >=0.7.0
Requires-Dist: torch >=2.0
